{
	"info": {
		"_postman_id": "dcd8fc73-9239-41ee-a5f7-f8f8b57f6346",
		"name": "Library Collection",
		"schema": "https://schema.getpostman.com/json/collection/v2.1.0/collection.json",
		"_exporter_id": "26011398"
	},
	"item": [
		{
			"name": "Admin",
			"item": [
				{
					"name": "Login admin",
					"request": {
						"method": "POST",
						"header": [],
						"body": {
							"mode": "raw",
							"raw": "{\n    \"email\":\"admin@zignuts.com\",\n    \"password\":\"VeryStrong@Pwd9812\"\n}",
							"options": {
								"raw": {
									"language": "json"
								}
							}
						},
						"url": {
							"raw": "{{base_url}}/admin/login",
							"host": [
								"{{base_url}}"
							],
							"path": [
								"admin",
								"login"
							]
						}
					},
					"response": []
				},
				{
					"name": "Logout admin",
					"request": {
						"auth": {
							"type": "bearer",
							"bearer": [
								{
									"key": "token",
									"value": "{{admin_jwt}}",
									"type": "string"
								}
							]
						},
						"method": "GET",
						"header": [],
						"url": {
							"raw": "{{base_url}}/admin/logout",
							"host": [
								"{{base_url}}"
							],
							"path": [
								"admin",
								"logout"
							]
						}
					},
					"response": []
				},
				{
					"name": "Add category",
					"request": {
						"auth": {
							"type": "bearer",
							"bearer": [
								{
									"key": "token",
									"value": "{{admin_jwt}}",
									"type": "string"
								}
							]
						},
						"method": "POST",
						"header": [],
						"body": {
							"mode": "raw",
							"raw": "{\n    \"name\":\"Classic\"\n}",
							"options": {
								"raw": {
									"language": "json"
								}
							}
						},
						"url": {
							"raw": "{{base_url}}/category",
							"host": [
								"{{base_url}}"
							],
							"path": [
								"category"
							]
						}
					},
					"response": []
				},
				{
					"name": "Listing category",
					"request": {
						"auth": {
							"type": "bearer",
							"bearer": [
								{
									"key": "token",
									"value": "{{admin_jwt}}",
									"type": "string"
								}
							]
						},
						"method": "GET",
						"header": [],
						"url": {
							"raw": "{{base_url}}/category",
							"host": [
								"{{base_url}}"
							],
							"path": [
								"category"
							],
							"query": [
								{
									"key": "page",
									"value": "1",
									"disabled": true
								},
								{
									"key": "limit",
									"value": "2",
									"disabled": true
								}
							]
						}
					},
					"response": []
				},
				{
					"name": "Edit category",
					"request": {
						"auth": {
							"type": "bearer",
							"bearer": [
								{
									"key": "token",
									"value": "{{admin_jwt}}",
									"type": "string"
								}
							]
						},
						"method": "PATCH",
						"header": [],
						"body": {
							"mode": "raw",
							"raw": "{\n    \"name\":\"Classic\"\n}",
							"options": {
								"raw": {
									"language": "json"
								}
							}
						},
						"url": {
							"raw": "{{base_url}}/category/3b3fc98a-61c9-4c0a-b823-fb277c0c4aa2",
							"host": [
								"{{base_url}}"
							],
							"path": [
								"category",
								"3b3fc98a-61c9-4c0a-b823-fb277c0c4aa2"
							]
						}
					},
					"response": []
				},
				{
					"name": "Delete category",
					"request": {
						"auth": {
							"type": "bearer",
							"bearer": [
								{
									"key": "token",
									"value": "{{admin_jwt}}",
									"type": "string"
								}
							]
						},
						"method": "DELETE",
						"header": [],
						"url": {
							"raw": "{{base_url}}/category/3b3fc98a-61c9-4c0a-b823-fb277c0c4aa2",
							"host": [
								"{{base_url}}"
							],
							"path": [
								"category",
								"3b3fc98a-61c9-4c0a-b823-fb277c0c4aa2"
							]
						}
					},
					"response": []
				},
				{
					"name": "Add author",
					"request": {
						"auth": {
							"type": "bearer",
							"bearer": [
								{
									"key": "token",
									"value": "{{admin_jwt}}",
									"type": "string"
								}
							]
						},
						"method": "POST",
						"header": [],
						"body": {
							"mode": "raw",
							"raw": "{\n    \"name\":\"author6\"\n}",
							"options": {
								"raw": {
									"language": "json"
								}
							}
						},
						"url": {
							"raw": "{{base_url}}/author",
							"host": [
								"{{base_url}}"
							],
							"path": [
								"author"
							]
						}
					},
					"response": []
				},
				{
					"name": "Listing author",
					"request": {
						"auth": {
							"type": "bearer",
							"bearer": [
								{
									"key": "token",
									"value": "{{admin_jwt}}",
									"type": "string"
								}
							]
						},
						"method": "GET",
						"header": [],
						"url": {
							"raw": "{{base_url}}/author",
							"host": [
								"{{base_url}}"
							],
							"path": [
								"author"
							]
						}
					},
					"response": []
				},
				{
					"name": "Edit author",
					"request": {
						"auth": {
							"type": "bearer",
							"bearer": [
								{
									"key": "token",
									"value": "{{admin_jwt}}",
									"type": "string"
								}
							]
						},
						"method": "PATCH",
						"header": [],
						"body": {
							"mode": "raw",
							"raw": "{\n    \"name\":\"Author23456\"\n}",
							"options": {
								"raw": {
									"language": "json"
								}
							}
						},
						"url": {
							"raw": "{{base_url}}/author/ca834838-de64-42e8-bb4c-ebd8f806e06d",
							"host": [
								"{{base_url}}"
							],
							"path": [
								"author",
								"ca834838-de64-42e8-bb4c-ebd8f806e06d"
							]
						}
					},
					"response": []
				},
				{
					"name": "Delete author",
					"request": {
						"auth": {
							"type": "bearer",
							"bearer": [
								{
									"key": "token",
									"value": "{{admin_jwt}}",
									"type": "string"
								}
							]
						},
						"method": "DELETE",
						"header": [],
						"url": {
							"raw": "{{base_url}}/author/ca834838-de64-42e8-bb4c-ebd8f806e06d",
							"host": [
								"{{base_url}}"
							],
							"path": [
								"author",
								"ca834838-de64-42e8-bb4c-ebd8f806e06d"
							]
						}
					},
					"response": []
				},
				{
					"name": "Add book",
					"request": {
						"auth": {
							"type": "bearer",
							"bearer": [
								{
									"key": "token",
									"value": "{{admin_jwt}}",
									"type": "string"
								}
							]
						},
						"method": "POST",
						"header": [],
						"body": {
							"mode": "formdata",
							"formdata": [
								{
									"key": "name",
									"value": "book1",
									"type": "text"
								},
								{
									"key": "author",
									"value": "author1",
									"type": "text"
								},
								{
									"key": "price",
									"value": "111",
									"type": "text"
								},
								{
									"key": "category",
									"value": "Classic",
									"type": "text"
								},
								{
									"key": "publishYear",
									"value": "2001",
									"type": "text"
								},
								{
									"key": "thumb",
									"type": "file",
									"src": "/Users/ztlab140/Documents/sails/library-management/images/book1img.jpg"
								}
							]
						},
						"url": {
							"raw": "{{base_url}}/book",
							"host": [
								"{{base_url}}"
							],
							"path": [
								"book"
							]
						}
					},
					"response": []
				},
				{
					"name": "Listing book",
					"request": {
						"auth": {
							"type": "bearer",
							"bearer": [
								{
									"key": "token",
									"value": "{{admin_jwt}}",
									"type": "string"
								}
							]
						},
						"method": "GET",
						"header": [],
						"url": {
							"raw": "{{base_url}}/book",
							"host": [
								"{{base_url}}"
							],
							"path": [
								"book"
							]
						}
					},
					"response": []
				},
				{
					"name": "Edit book",
					"request": {
						"auth": {
							"type": "bearer",
							"bearer": [
								{
									"key": "token",
									"value": "{{admin_jwt}}",
									"type": "string"
								}
							]
						},
						"method": "PATCH",
						"header": [],
						"body": {
							"mode": "raw",
							"raw": "{\n    \"publishYear\":\"20001\"\n}",
							"options": {
								"raw": {
									"language": "json"
								}
							}
						},
						"url": {
							"raw": "{{base_url}}/book/9d030420-bedd-48e6-b25f-8777d144774d",
							"host": [
								"{{base_url}}"
							],
							"path": [
								"book",
								"9d030420-bedd-48e6-b25f-8777d144774d"
							]
						}
					},
					"response": []
				},
				{
					"name": "Delete book",
					"request": {
						"auth": {
							"type": "bearer",
							"bearer": [
								{
									"key": "token",
									"value": "{{admin_jwt}}",
									"type": "string"
								}
							]
						},
						"method": "DELETE",
						"header": [],
						"url": {
							"raw": "{{base_url}}/book/9d030420-bedd-48e6-b25f-8777d144774d",
							"host": [
								"{{base_url}}"
							],
							"path": [
								"book",
								"9d030420-bedd-48e6-b25f-8777d144774d"
							]
						}
					},
					"response": []
				},
				{
					"name": "Issue book to user",
					"request": {
						"auth": {
							"type": "bearer",
							"bearer": [
								{
									"key": "token",
									"value": "{{admin_jwt}}",
									"type": "string"
								}
							]
						},
						"method": "POST",
						"header": [],
						"body": {
							"mode": "raw",
							"raw": "{\n    \"book\":\"book1\",\n    \"issuedTo\":\"user1\"\n}",
							"options": {
								"raw": {
									"language": "json"
								}
							}
						},
						"url": {
							"raw": "{{base_url}}/history",
							"host": [
								"{{base_url}}"
							],
							"path": [
								"history"
							]
						}
					},
					"response": []
				},
				{
					"name": "Return book from user",
					"request": {
						"auth": {
							"type": "bearer",
							"bearer": [
								{
									"key": "token",
									"value": "{{admin_jwt}}",
									"type": "string"
								}
							]
						},
						"method": "PATCH",
						"header": [],
						"url": {
							"raw": "{{base_url}}/history/:id",
							"host": [
								"{{base_url}}"
							],
							"path": [
								"history",
								":id"
							],
							"variable": [
								{
									"key": "id",
									"value": null
								}
							]
						}
					},
					"response": []
				},
				{
					"name": "Listing history of issued books by book ID",
					"request": {
						"auth": {
							"type": "bearer",
							"bearer": [
								{
									"key": "token",
									"value": "{{admin_jwt}}",
									"type": "string"
								}
							]
						},
						"method": "GET",
						"header": [],
						"url": {
							"raw": "{{base_url}}/history/:id",
							"host": [
								"{{base_url}}"
							],
							"path": [
								"history",
								":id"
							],
							"variable": [
								{
									"key": "id",
									"value": null
								}
							]
						}
					},
					"response": []
				}
			]
		},
		{
			"name": "User",
			"item": [
				{
					"name": "Signup user",
					"request": {
						"method": "POST",
						"header": [],
						"body": {
							"mode": "raw",
							"raw": "{\n    \"firstName\":\"user1fn\",\n    \"lastName\":\"user1ln\",\n    \"email\":\"user1@gmail.com\",\n    \"password\":\"user1#PW\",\n    \"username\":\"user1un\"\n}",
							"options": {
								"raw": {
									"language": "json"
								}
							}
						},
						"url": {
							"raw": "{{base_url}}/user/register",
							"host": [
								"{{base_url}}"
							],
							"path": [
								"user",
								"register"
							]
						}
					},
					"response": []
				},
				{
					"name": "Login user",
					"request": {
						"method": "POST",
						"header": [],
						"body": {
							"mode": "raw",
							"raw": "{\n    \"email\":\"user1@gmail.com\",\n    \"password\":\"user1#PW\"\n}",
							"options": {
								"raw": {
									"language": "json"
								}
							}
						},
						"url": {
							"raw": "{{base_url}}/user/login",
							"host": [
								"{{base_url}}"
							],
							"path": [
								"user",
								"login"
							]
						}
					},
					"response": []
				},
				{
					"name": "Logout user",
					"request": {
						"auth": {
							"type": "bearer",
							"bearer": [
								{
									"key": "token",
									"value": "{{user_jwt}}",
									"type": "string"
								}
							]
						},
						"method": "GET",
						"header": [],
						"url": {
							"raw": "{{base_url}}/user/logout",
							"host": [
								"{{base_url}}"
							],
							"path": [
								"user",
								"logout"
							]
						}
					},
					"response": []
				},
				{
					"name": "Listing available books, search by book name, category name, author name",
					"request": {
						"auth": {
							"type": "bearer",
							"bearer": [
								{
									"key": "token",
									"value": "{{user_jwt}}",
									"type": "string"
								}
							]
						},
						"method": "GET",
						"header": [],
						"url": {
							"raw": "{{base_url}}/book/user",
							"host": [
								"{{base_url}}"
							],
							"path": [
								"book",
								"user"
							]
						}
					},
					"response": []
				}
			]
		}
	],
	"event": [
		{
			"listen": "prerequest",
			"script": {
				"type": "text/javascript",
				"exec": [
					""
				]
			}
		},
		{
			"listen": "test",
			"script": {
				"type": "text/javascript",
				"exec": [
					""
				]
			}
		}
	],
	"variable": [
		{
			"key": "base_url",
			"value": "http://localhost:1337",
			"type": "string"
		},
		{
			"key": "admin_jwt",
			"value": "eyJhbGciOiJIUzI1NiIsInR5cCI6IkpXVCJ9.eyJpZCI6IjY3MzM3OGEyLWVmYTUtNGNjOS04YTM5LWE2ODZjMjMwZTNiMyIsImlhdCI6MTY3OTQ4NTQ1OCwiZXhwIjoxNjgyMDc3NDU4LCJpc3MiOiJodHRwczovL3d3dy56aWdudXRzLmNvbSJ9.Pi-5BWt3TKoqOYQa7UvIa844CQbXJnlh7dA8kiWRmDU",
			"type": "string"
		},
		{
			"key": "user_jwt",
			"value": "eyJhbGciOiJIUzI1NiIsInR5cCI6IkpXVCJ9.eyJpZCI6IjJmMmNjMzk3LTc2ZTAtNGU0NC1iODk4LTYzZjMyM2Y1NmM5NyIsImlhdCI6MTY3OTQ4NjU2MywiZXhwIjoxNjgyMDc4NTYzLCJpc3MiOiJodHRwczovL3d3dy56aWdudXRzLmNvbSJ9.p3mIK4E2Hvi9duVRF-3XDK4e30UlvYP2OSWXoF-B3YU",
			"type": "string"
		}
	]
}